{
	"EVOLVER_CHANNEL": "1000",
	"CLINIC_CHANNEL": "1001",
	"MODIFIER_CHANNEL": "1002",
	"DEATH_CHANNEL": "1003",
	"SCREENSHOT_CHANNEL": "1004",

	"SIZE_MUTATION_RATE": "0.6",
	"SIZE_MUTATION_STRENGTH": "1",
	"THRESHOLD": "0",
	"CPPN_GRID_STARTING_SIZE": "5",
	"MATRIX_MUTATION_RATE" : "0.5",
	"MATRIX_MUTATION_STRENGTH" : "1",

	"ARENA_SIZE": "30",
	"NUMBER_OF_MODULES": "40",
	"INITIAL_POPULATION": "6",
	"SHAPE_ENCODING": "CPPN",
	"CLINIC_SAFE_DISTANCE": "5",

	"MATING_TIME": "100",
	"DYING_TIME": "1000",
	"INFANCY_DURATION": "500",
	"SEND_FITNESS_TO_EVOLVER_INTERVAL": "10",
	"ROOMBOT_WAITING_TIME": "10",
	"MATURE_TIME_TO_LIVE": "1000",
	"CHECK_EVOLUTION_END_INTERVAL": "60"
}